Workbook

Sheet READ ME 
A1: FamInsureCo Data Analysis
A22: Now it's time for us to get started on our Data Analysis for FamInsureCo!
A23: As we've mentioned previously, there are a number of questions Management have expressed an interest in answering.
A25: • Do individuals who tend to have a higher Body Mass Index (BMI), have higher insurance costs? • Does region (geography) appear to have any impact on insurance costs? • Does the biological marker have any bearing with insurance costs? • Does the biological marker have any impact regarding insurance costs? (i.e. Do Men have higher insurance costs than women?) • Does smoking have any impact regarding insurance costs? • Do any correlations exist between medical charges and lifestyle?
A27: We'll seek to tackle this assignment in three parts.
A29: Firstly, you'll work on the Basic Desc. Statistics Tab where you'll make use of your knowledge of descriptive stats, to visualise the Medical Charges data. You'll be using the data in the FamInsureCo. Desc Stats Data Tab.
A30: Secondly, you'll work on the Intermediate Desc. Statistics Tab where you'll make use of your intermediate statistics knowledge, where you'll apply box and whisker plots, correlation analyses and multiple regression to identify the variables that have a linear relationship with medical charges. You'll be using the data in the FamInsureCo Int. Stats Data Tab.
A31: Thirdly, you'll then build out your presentation where you'll synthesize your insights for the FamInsureCo team!
A33: With this in mind, let's get started!
A35: Definitions
A36: We've included a high-level breakdown that explains the different columns you'll deal with in the FamInsureCo Desc. Stats Data Tab
A38: Age | B38: This column provides information on how old the individual is.
A39: Biological Marker | B39: This is a column filled with the individuals biological marker (i.e. Are they male or female).
A40: BMI | B40: This is a column that represents the Body Mass Index (BMI) of the respective individual. This is a commonly used metric to assess overhealth.
A41: Smoker | B41: This is a column that indicates whether the individual is a smoker or not.
A42: Region | B42: This is a column that indicates the geographical location of where the individual resides (i.e. Northwest, Northeast etc.)
A43: Medical_Insurance_Charges | B43: This is a column that represents the medical insurance charges incurred by that individual.

Sheet FamInsureCo Desc. Stats Data
A1: age | B1: biological marker | C1: bmi | D1: smoker | E1: region | F1: medical_insurance_charges | G1: BMI_Categorisation | H1: Age_Classification
A2: 18 | B2: female | C2: 20.79 | D2: no | E2: southeast | F2: 1607.5101 | G2: {=_xlfn.IFS(C2<=18.5,"Underweight",AND(C2>18.5,C2<=24.9),"Healthy",AND(C2>24.9,C2<=29.9),"Slightly Overweight",C2>29.9,"Overweight")} -> Healthy | H2: {=_xlfn.IFS(A2<=25,"Young Adult",AND(A2>=26,A2<=35),"Adult",AND(A2>=36,A2<=59),"Mature Age Adult",A2>=60,"Senior")} -> Young Adult
A3: 18 | B3: female | C3: 24.09 | D3: no | E3: southeast | F3: 2201.0971 | G3: {=_xlfn.IFS(C3<=18.5,"Underweight",AND(C3>18.5,C3<=24.9),"Healthy",AND(C3>24.9,C3<=29.9),"Slightly Overweight",C3>29.9,"Overweight")} -> Healthy | H3: {=_xlfn.IFS(A3<=25,"Young Adult",AND(A3>=26,A3<=35),"Adult",AND(A3>=36,A3<=59),"Mature Age Adult",A3>=60,"Senior")} -> Young Adult
A4: 19 | B4: female | C4: 24.7 | D4: no | E4: southwest | F4: 1737.376 | G4: {=_xlfn.IFS(C4<=18.5,"Underweight",AND(C4>18.5,C4<=24.9),"Healthy",AND(C4>24.9,C4<=29.9),"Slightly Overweight",C4>29.9,"Overweight")} -> Healthy | H4: {=_xlfn.IFS(A4<=25,"Young Adult",AND(A4>=26,A4<=35),"Adult",AND(A4>=36,A4<=59),"Mature Age Adult",A4>=60,"Senior")} -> Young Adult
A5: 19 | B5: female | C5: 24.51 | D5: no | E5: northwest | F5: 2709.1119 | G5: {=_xlfn.IFS(C5<=18.5,"Underweight",AND(C5>18.5,C5<=24.9),"Healthy",AND(C5>24.9,C5<=29.9),"Slightly Overweight",C5>29.9,"Overweight")} -> Healthy | H5: {=_xlfn.IFS(A5<=25,"Young Adult",AND(A5>=26,A5<=35),"Adult",AND(A5>=36,A5<=59),"Mature Age Adult",A5>=60,"Senior")} -> Young Adult
A6: 19 | B6: female | C6: 22.515 | D6: no | E6: northwest | F6: 2117.3389 | G6: {=_xlfn.IFS(C6<=18.5,"Underweight",AND(C6>18.5,C6<=24.9),"Healthy",AND(C6>24.9,C6<=29.9),"Slightly Overweight",C6>29.9,"Overweight")} -> Healthy | H6: {=_xlfn.IFS(A6<=25,"Young Adult",AND(A6>=26,A6<=35),"Adult",AND(A6>=36,A6<=59),"Mature Age Adult",A6>=60,"Senior")} -> Young Adult
A7: 19 | B7: female | C7: 23.4 | D7: no | E7: southwest | F7: 2913.569 | G7: {=_xlfn.IFS(C7<=18.5,"Underweight",AND(C7>18.5,C7<=24.9),"Healthy",AND(C7>24.9,C7<=29.9),"Slightly Overweight",C7>29.9,"Overweight")} -> Healthy | H7: {=_xlfn.IFS(A7<=25,"Young Adult",AND(A7>=26,A7<=35),"Adult",AND(A7>=36,A7<=59),"Mature Age Adult",A7>=60,"Senior")} -> Young Adult
A8: 19 | B8: female | C8: 24.605 | D8: no | E8: northwest | F8: 2709.244 | G8: {=_xlfn.IFS(C8<=18.5,"Underweight",AND(C8>18.5,C8<=24.9),"Healthy",AND(C8>24.9,C8<=29.9),"Slightly Overweight",C8>29.9,"Overweight")} -> Healthy | H8: {=_xlfn.IFS(A8<=25,"Young Adult",AND(A8>=26,A8<=35),"Adult",AND(A8>=36,A8<=59),"Mature Age Adult",A8>=60,"Senior")} -> Young Adult
A9: 19 | B9: female | C9: 18.6 | D9: no | E9: southwest | F9: 1728.897 | G9: {=_xlfn.IFS(C9<=18.5,"Underweight",AND(C9>18.5,C9<=24.9),"Healthy",AND(C9>24.9,C9<=29.9),"Slightly Overweight",C9>29.9,"Overweight")} -> Healthy | H9: {=_xlfn.IFS(A9<=25,"Young Adult",AND(A9>=26,A9<=35),"Adult",AND(A9>=36,A9<=59),"Mature Age Adult",A9>=60,"Senior")} -> Young Adult
A10: 19 | B10: female | C10: 20.6 | D10: no | E10: southwest | F10: 1731.677 | G10: {=_xlfn.IFS(C10<=18.5,"Underweight",AND(C10>18.5,C10<=24.9),"Healthy",AND(C10>24.9,C10<=29.9),"Slightly Overweight",C10>29.9,"Overweight")} -> Healthy | H10: {=_xlfn.IFS(A10<=25,"Young Adult",AND(A10>=26,A10<=35),"Adult",AND(A10>=36,A10<=59),"Mature Age Adult",A10>=60,"Senior")} -> Young Adult
A11: 21 | B11: female | C11: 21.89 | D11: no | E11: southeast | F11: 3180.5101 | G11: {=_xlfn.IFS(C11<=18.5,"Underweight",AND(C11>18.5,C11<=24.9),"Healthy",AND(C11>24.9,C11<=29.9),"Slightly Overweight",C11>29.9,"Overweight")} -> Healthy | H11: {=_xlfn.IFS(A11<=25,"Young Adult",AND(A11>=26,A11<=35),"Adult",AND(A11>=36,A11<=59),"Mature Age Adult",A11>=60,"Senior")} -> Young Adult
A12: 21 | B12: female | C12: 22.135 | D12: no | E12: northeast | F12: 2585.8506 | G12: {=_xlfn.IFS(C12<=18.5,"Underweight",AND(C12>18.5,C12<=24.9),"Healthy",AND(C12>24.9,C12<=29.9),"Slightly Overweight",C12>29.9,"Overweight")} -> Healthy | H12: {=_xlfn.IFS(A12<=25,"Young Adult",AND(A12>=26,A12<=35),"Adult",AND(A12>=36,A12<=59),"Mature Age Adult",A12>=60,"Senior")} -> Young Adult
A13: 22 | B13: female | C13: 24.3 | D13: no | E13: southwest | F13: 2150.469 | G13: {=_xlfn.IFS(C13<=18.5,"Underweight",AND(C13>18.5,C13<=24.9),"Healthy",AND(C13>24.9,C13<=29.9),"Slightly Overweight",C13>29.9,"Overweight")} -> Healthy | H13: {=_xlfn.IFS(A13<=25,"Young Adult",AND(A13>=26,A13<=35),"Adult",AND(A13>=36,A13<=59),"Mature Age Adult",A13>=60,"Senior")} -> Young Adult
... A1339: 18 | B1339: male | C1339: 17.29 | D1339: yes | E1339: northeast | F1339: 12829.455 | G1339: {=_xlfn.IFS(C1339<=18.5,"Underweight",AND(C1339>18.5,C1339<=24.9),"Healthy",AND(C1339>24.9,C1339<=29.9),"Slightly Overweight",C1339>29.9,"Overweight")} -> Underweight | H1339: {=_xlfn.IFS(A1339<=25,"Young Adult",AND(A1339>=26,A1339<=35),"Adult",AND(A1339>=36,A1339<=59),"Mature Age Adult",A1339>=60,"Senior")} -> Young Adult

Sheet Basic Desc. Statistics
A1: Descriptive Statistics Analysis - Part I
A2: We've introduced you now to a number of basic statistical concepts.
A3: Whilst statistics might seem scary, it's critical in enabling us to identify trends that we can then drill down and ask 'why' with some of our more seasoned colleagues.
A5: An example of this might be with Walmart; Walmart may have seen a customer trend that shoppers most frequently enter the store on the Saturday Morning. As such, they may include more promotional specials over the weekend period and ask the respective analytics team to run some more advanced statistics (i.e. correlation) to assess whether there is a trend between promotional specials shown on the Saturday Morning and sales over that period.
A7: With what you've learned, let's take a look at FamInsureCo's Data and see what trends we can identify using the tools of Descriptive Statistics!
A9: Let's get started!
A11: As with all data analysis exercises, looking at the numbers in a stationary way (i.e. table form as opposed to graphical) can make trend realisation difficult.
A12: This is especially the case where we have large volumes of data points to visualise.
A13: This is why we turn towards a graphical view of our data - viewing the data in this manner enables us to more accurately pick out abnormal periods which we can then hone in on.
A14: Q1. Interpret the scatter plot visualization we've created for you here. Using your knowledge of Scatter Plots - what do you observe in terms of the relationship between BMI and Medical Insurance Charges? Put your answer in the box to the right of the image.
A15: Note: We've included an example for you so you'll know what to expect when you create your visualisation!
A16: Place your Scatter Plot Below
E18: What do you observe about the Scatter Plot to the left?
E19: As BMI increases, medical insurance charges also increases
E20: BMI above 30 tends to have higher medical insurance charges
E21: There's a significant portion of data points with lower BMIs that are below 30, which have relatively lower insurance charges, mostly under $20,000.
E22: Outliers exist at all BMI levels, leaving some variation in the data
E23: Outliers include some individuals with very high BMIs (40-50) as well as some moderate BMIs that both have high insurance charges.
E24: Since there are so many outliers, we can note that while BMI influences charges, other factors could also contribute to higher insurance charges.
A36: Now you might conclude drawing any strong conclusions is challenging due to the granularity of the data.
A37: Let's introduce some additional categories to make visualizing these trends a bit easier.
A38: Let's break this down by reclassifying the BMI data into different categories.
A40: The CDC provides the following BMI breakdowns:
A41: BMI <= 18.5: Underweight
A42: BMI greater than 18.5 and less than or equal to 24.9: Healthy
A43: BMI greater 24.9 and less than or equal to 29.9: Slightly Overweight
A44: BMI greater than 29.9 or higher: Overweight
A46: Q2A. Create a new column titled BMI_Categorisation in the FamInsureCo dataset that categories the BMI Column using the criteria listed above.
A47: Hint: You'll have to use the IFS Clause to help you with creating this new column e.g. = IFS(Some_Criteria,"Outcome A", Some_Other_Criteria, "Outcome_B"…)
A49: Q2B. Using the BMI_Categorization column you've made, complete the table below. Upon completion of this table, create a Scatter Plot showcasing the total # of individuals per BMI_Categorization versus the Average Medical Insurance Charges. Please ensure you have the Y-Axis set to medical_insurance_charges and the X-Axis set to the total # of individuals per BMI_Categorization.
A50: Hint: Think about how you can use COUNTIFS to get the Total # of Individuals per weight classification in your BMI_Categorization column!
... A52: Place your chart below here!
C55: Underweight | D55: Healthy | E55: Slightly Overweight | F55: Overweight
B56: Total # of Individuals | C56: =COUNTIF('FamInsureCo Desc. Stats Data'!$G:$G,'Basic Desc. Statistics'!C55) -> 21 | D56: =COUNTIF('FamInsureCo Desc. Stats Data'!$G:$G,'Basic Desc. Statistics'!D55) -> 221 | E56: =COUNTIF('FamInsureCo Desc. Stats Data'!$G:$G,'Basic Desc. Statistics'!E55) -> 380 | F56: =COUNTIF('FamInsureCo Desc. Stats Data'!$G:$G,'Basic Desc. Statistics'!F55) -> 716
B57: Average Medical Insurance Charges | C57: =AVERAGEIF('FamInsureCo Desc. Stats Data'!$G:$G,'Basic Desc. Statistics'!C55,'FamInsureCo Desc. Stats Data'!$F:$F) -> 8657.6207 | D57: =AVERAGEIF('FamInsureCo Desc. Stats Data'!$G:$G,'Basic Desc. Statistics'!D55,'FamInsureCo Desc. Stats Data'!$F:$F) -> 10404.9 | E57: =AVERAGEIF('FamInsureCo Desc. Stats Data'!$G:$G,'Basic Desc. Statistics'!E55,'FamInsureCo Desc. Stats Data'!$F:$F) -> 11006.81 | F57: =AVERAGEIF('FamInsureCo Desc. Stats Data'!$G:$G,'Basic Desc. Statistics'!F55,'FamInsureCo Desc. Stats Data'!$F:$F) -> 15491.542
A77: What if we were to dive one level deeper as part of our Micro Analysis and include Smoking Status into the mix? Do we see any observable shift in the relationship between Medical Charges, Smoking Status and BMI? Let's take a look!
A78: Q3. Create a scatter plot highlighting the Medical Insurance Charge and BMI, when Smoking Status = Yes.
A79: What do you observe?
A80: Note: We've created the Scatter Plot for you when Smoking = No, to help you get started!
A81: BMI vs Medical Insurance Charge (Smoking Status = No ) | E81: BMI vs Medical Insurance Charge (Smoking Status = Yes )
D99: *Observations: with smokers medical insurance charges and increased BMI have a more powerful correlation in regards to impacting each other. BMI over 30 results in much higher medical insurance charges for smokers vs. non-smokers.
A100: Q4. Create two histogram distributions using the Medical Insurance Data, filtered on Smoker = Yes and Smoker = No. Ensure you set the Bin Width to $5,000 for both Histograms.
A101: Comparing the two histogram distributions - what do you observe in relation to medical charges?
A102: Note: Don't forget that you'll need to filter the data in the FamInsureCo Dataset before creating your Histogram. Once you've filtered the data, don't forget to paste your Histogram as an image so your chart won't change when you modify your filter.
A120: *Observation: the majority of non-smokers have lower medical insurance charges vs. smokers. Smokers medical insurance charges vary with many charges being both low and on the higher end.
A121: Now it appears that there is a clear pricing difference between individuals who smoke and invididuals who don't.
A122: Could it be that the older we get, the higher our insurance charges? This could make sense, but let's verify this with our data to confirm whether or not this is valid!
A123: Q5A. Create a new column called Age_Classification which classifies the Age Column based off the following criteria
A124: 18 - 25 = Young Adult
A125: 26 - 35 = Adult
A126: 36 - 59 = Mature Age Adult
A127: >=60 | B127: Senior
A129: Q5B. Complete the table below and create a Stacked Column Chart showing the Average Medical Insurance Charges per Age Group. What do you observe?
A130: Note: We've included an example for you so you'll know what to expect when you create your visualisation!
B132: Age Grouping | C132: Young Adult | D132: Adult | E132: Mature Age Adult | F132: Senior
B133: Avg. Medical Insurance Charges | C133: =AVERAGEIF('FamInsureCo Desc. Stats Data'!$H:$H,'Basic Desc. Statistics'!C132,'FamInsureCo Desc. Stats Data'!$F:$F) -> 9087.0158 | D133: =AVERAGEIF('FamInsureCo Desc. Stats Data'!$H:$H,'Basic Desc. Statistics'!D132,'FamInsureCo Desc. Stats Data'!$F:$F) -> 10495.163 | E133: =AVERAGEIF('FamInsureCo Desc. Stats Data'!$H:$H,'Basic Desc. Statistics'!E132,'FamInsureCo Desc. Stats Data'!$F:$F) -> 14984.954 | F133: =AVERAGEIF('FamInsureCo Desc. Stats Data'!$H:$H,'Basic Desc. Statistics'!F132,'FamInsureCo Desc. Stats Data'!$F:$F) -> 21248.022
B134: Avg. Medical Insurance Charges (Smoking = Yes ) | C134: =AVERAGEIFS('FamInsureCo Desc. Stats Data'!$F:$F,'FamInsureCo Desc. Stats Data'!$H:$H,'Basic Desc. Statistics'!C132,'FamInsureCo Desc. Stats Data'!$D:$D,"Yes") -> 27933.556 | D134: =AVERAGEIFS('FamInsureCo Desc. Stats Data'!$F:$F,'FamInsureCo Desc. Stats Data'!$H:$H,'Basic Desc. Statistics'!D132,'FamInsureCo Desc. Stats Data'!$D:$D,"Yes") -> 28281.654 | E134: =AVERAGEIFS('FamInsureCo Desc. Stats Data'!$F:$F,'FamInsureCo Desc. Stats Data'!$H:$H,'Basic Desc. Statistics'!E132,'FamInsureCo Desc. Stats Data'!$D:$D,"Yes") -> 34010.166 | F134: =AVERAGEIFS('FamInsureCo Desc. Stats Data'!$F:$F,'FamInsureCo Desc. Stats Data'!$H:$H,'Basic Desc. Statistics'!F132,'FamInsureCo Desc. Stats Data'!$D:$D,"Yes") -> 40630.695
B135: Avg. Medical Insurance Charges (Smoking = No) | C135: =AVERAGEIFS('FamInsureCo Desc. Stats Data'!$F:$F,'FamInsureCo Desc. Stats Data'!$H:$H,'Basic Desc. Statistics'!C132,'FamInsureCo Desc. Stats Data'!$D:$D,"No") -> 4003.9239 | D135: =AVERAGEIFS('FamInsureCo Desc. Stats Data'!$F:$F,'FamInsureCo Desc. Stats Data'!$H:$H,'Basic Desc. Statistics'!D132,'FamInsureCo Desc. Stats Data'!$D:$D,"No") -> 5796.8448 | E135: =AVERAGEIFS('FamInsureCo Desc. Stats Data'!$F:$F,'FamInsureCo Desc. Stats Data'!$H:$H,'Basic Desc. Statistics'!E132,'FamInsureCo Desc. Stats Data'!$D:$D,"No") -> 10410.189 | F135: =AVERAGEIFS('FamInsureCo Desc. Stats Data'!$F:$F,'FamInsureCo Desc. Stats Data'!$H:$H,'Basic Desc. Statistics'!F132,'FamInsureCo Desc. Stats Data'!$D:$D,"No") -> 15232.709
E136: =E134-E133 -> 19025.213 | F136: =F134-F133 -> 19382.673
E137: =(E134-E133)/E134 -> 0.55939781 | F137: =(F134-F133)/F134 -> 0.47704508
A151: *Observation: medical insurance charges increase overall as people age. Smokers still have much higher medical insurance charges than non-smokers, and their charges also increase as their age increases.
A153: Now we can clearly see there appears to be some very apparent visual trends regarding expenditures, smoking status and age.
A154: However, what about the individuals biological marker? Does there appear to be any noticeable differences between Male and Female medical expenditures?
A156: Q6. Complete the table below showcasing the Average Medical Insurance Charges for Males and Females, inclusive of their Smoker Status.
B158: Biological Marker | C158: Smoker Status = Yes | D158: Smoker Status = No
B159: Male Medical Insurance Charges | C159: =AVERAGEIFS('FamInsureCo Desc. Stats Data'!$F:$F,'FamInsureCo Desc. Stats Data'!$D:$D,"Yes",'FamInsureCo Desc. Stats Data'!$B:$B, "Male") -> 33042.006 | D159: =AVERAGEIFS('FamInsureCo Desc. Stats Data'!$F:$F,'FamInsureCo Desc. Stats Data'!$D:$D,"No",'FamInsureCo Desc. Stats Data'!$B:$B, "Male") -> 8087.2047
B160: Female Medical Insurance Charges | C160: =AVERAGEIFS('FamInsureCo Desc. Stats Data'!$F:$F,'FamInsureCo Desc. Stats Data'!$D:$D,"Yes",'FamInsureCo Desc. Stats Data'!$B:$B, "Female") -> 30678.996 | D160: =AVERAGEIFS('FamInsureCo Desc. Stats Data'!$F:$F,'FamInsureCo Desc. Stats Data'!$D:$D,"No",'FamInsureCo Desc. Stats Data'!$B:$B, "Female") -> 8762.2973
A161: *Observation: Males who smoke have higher average medical insurance charges compared to females that smoke. However females that do not smoke have slightly higher average medical insurance charges compared to males that do not smoke. The difference between smoking males & femals is greater than the difference between non-smoking males & females.
A163: And that's a wrap! Well done on getting through the Basics of descriptive statistics! Now back to the course and onto Intermediate Statistics!

Sheet FamInsureCo Int. Stats Data
A1: age | B1: bmi | C1: BMI_Healthy | D1: BMI_Overweight | E1: BMI_Slightly_Overweight | F1: BMI_Underweight | G1: Biological Marker | H1: Smoker | I1: southeast | J1: southwest | K1: northwest | L1: northeast | M1: Young Adult | N1: Adult | O1: Mature Age Adult | P1: Senior | Q1: medical_insurance_charges | R1: predicted_charges | S1: error | T1: error_pct | W1: Coefficient Values (Use this to build your regressive equation) for Q17
A2: 18 | B2: 20.79 | C2: 1 | D2: 0 | E2: 0 | F2: 0 | G2: 0 | H2: 0 | I2: 1 | J2: 0 | K2: 0 | L2: 0 | M2: 1 | N2: 0 | O2: 0 | P2: 0 | Q2: 1607.5101 | R2: =$X$2*A2+$X$3*B2+($X$4)*C2+$X$5*D2+($X$6)*E2+($X$7)*F2+($X$8)*G2+$X$9*H2+($X$10)*I2+($X$11)*J2+$X$12*K2+$X$13*L2+$X$14*M2+($X$15)*N2+($X$16)*O2+($X$17)*P2+($X$18) -> -45.318921 | S2: =Q2-R2 -> 1652.829 | T2: =(R2-Q2)/Q2 -> -1.028192 | W2: age | X2: 314.35099
A3: 18 | B3: 24.09 | C3: 1 | D3: 0 | E3: 0 | F3: 0 | G3: 0 | H3: 0 | I3: 1 | J3: 0 | K3: 0 | L3: 0 | M3: 1 | N3: 0 | O3: 0 | P3: 0 | Q3: 2201.0971 | R3: =$X$2*A3+$X$3*B3+($X$4)*C3+$X$5*D3+($X$6)*E3+($X$7)*F3+($X$8)*G3+$X$9*H3+($X$10)*I3+($X$11)*J3+$X$12*K3+$X$13*L3+$X$14*M3+($X$15)*N3+($X$16)*O3+($X$17)*P3+($X$18) -> 452.75079 | S3: =Q3-R3 -> 1748.3463 | T3: =(R3-Q3)/Q3 -> -0.79430676 | W3: bmi | X3: 150.93022
A4: 19 | B4: 24.7 | C4: 1 | D4: 0 | E4: 0 | F4: 0 | G4: 0 | H4: 0 | I4: 0 | J4: 1 | K4: 0 | L4: 0 | M4: 1 | N4: 0 | O4: 0 | P4: 0 | Q4: 1737.376 | R4: =$X$2*A4+$X$3*B4+($X$4)*C4+$X$5*D4+($X$6)*E4+($X$7)*F4+($X$8)*G4+$X$9*H4+($X$10)*I4+($X$11)*J4+$X$12*K4+$X$13*L4+$X$14*M4+($X$15)*N4+($X$16)*O4+($X$17)*P4+($X$18) -> 856.56032 | S4: =Q4-R4 -> 880.81568 | T4: =(R4-Q4)/Q4 -> -0.50698046 | W4: BMI_Healthy | X4: -2875.5181
A5: 19 | B5: 24.51 | C5: 1 | D5: 0 | E5: 0 | F5: 0 | G5: 0 | H5: 0 | I5: 0 | J5: 0 | K5: 1 | L5: 0 | M5: 1 | N5: 0 | O5: 0 | P5: 0 | Q5: 2709.1119 | R5: =$X$2*A5+$X$3*B5+($X$4)*C5+$X$5*D5+($X$6)*E5+($X$7)*F5+($X$8)*G5+$X$9*H5+($X$10)*I5+($X$11)*J5+$X$12*K5+$X$13*L5+$X$14*M5+($X$15)*N5+($X$16)*O5+($X$17)*P5+($X$18) -> 1377.3136 | S5: =Q5-R5 -> 1331.7983 | T5: =(R5-Q5)/Q5 -> -0.49159958 | W5: BMI_Overweight | X5: 0
A6: 19 | B6: 22.515 | C6: 1 | D6: 0 | E6: 0 | F6: 0 | G6: 0 | H6: 0 | I6: 0 | J6: 0 | K6: 1 | L6: 0 | M6: 1 | N6: 0 | O6: 0 | P6: 0 | Q6: 2117.3389 | R6: =$X$2*A6+$X$3*B6+($X$4)*C6+$X$5*D6+($X$6)*E6+($X$7)*F6+($X$8)*G6+$X$9*H6+($X$10)*I6+($X$11)*J6+$X$12*K6+$X$13*L6+$X$14*M6+($X$15)*N6+($X$16)*O6+($X$17)*P6+($X$18) -> 1076.2079 | S6: =Q6-R6 -> 1041.131 | T6: =(R6-Q6)/Q6 -> -0.49171676 | W6: BMI_Slightly_Overweight | X6: -2592.2956
A7: 19 | B7: 23.4 | C7: 1 | D7: 0 | E7: 0 | F7: 0 | G7: 0 | H7: 0 | I7: 0 | J7: 1 | K7: 0 | L7: 0 | M7: 1 | N7: 0 | O7: 0 | P7: 0 | Q7: 2913.569 | R7: =$X$2*A7+$X$3*B7+($X$4)*C7+$X$5*D7+($X$6)*E7+($X$7)*F7+($X$8)*G7+$X$9*H7+($X$10)*I7+($X$11)*J7+$X$12*K7+$X$13*L7+$X$14*M7+($X$15)*N7+($X$16)*O7+($X$17)*P7+($X$18) -> 660.35104 | S7: =Q7-R7 -> 2253.218 | T7: =(R7-Q7)/Q7 -> -0.77335322 | W7: BMI_Underweight | X7: -3294.8153
A8: 19 | B8: 24.605 | C8: 1 | D8: 0 | E8: 0 | F8: 0 | G8: 0 | H8: 0 | I8: 0 | J8: 0 | K8: 1 | L8: 0 | M8: 1 | N8: 0 | O8: 0 | P8: 0 | Q8: 2709.244 | R8: =$X$2*A8+$X$3*B8+($X$4)*C8+$X$5*D8+($X$6)*E8+($X$7)*F8+($X$8)*G8+$X$9*H8+($X$10)*I8+($X$11)*J8+$X$12*K8+$X$13*L8+$X$14*M8+($X$15)*N8+($X$16)*O8+($X$17)*P8+($X$18) -> 1391.652 | S8: =Q8-R8 -> 1317.5919 | T8: =(R8-Q8)/Q8 -> -0.48633197 | W8: Biological Marker | X8: -113.82489
A9: 19 | B9: 18.6 | C9: 1 | D9: 0 | E9: 0 | F9: 0 | G9: 0 | H9: 0 | I9: 0 | J9: 1 | K9: 0 | L9: 0 | M9: 1 | N9: 0 | O9: 0 | P9: 0 | Q9: 1728.897 | R9: =$X$2*A9+$X$3*B9+($X$4)*C9+$X$5*D9+($X$6)*E9+($X$7)*F9+($X$8)*G9+$X$9*H9+($X$10)*I9+($X$11)*J9+$X$12*K9+$X$13*L9+$X$14*M9+($X$15)*N9+($X$16)*O9+($X$17)*P9+($X$18) -> -64.113992 | S9: =Q9-R9 -> 1793.011 | T9: =(R9-Q9)/Q9 -> -1.0370838 | W9: Smoker | X9: 23881.962
A10: 19 | B10: 20.6 | C10: 1 | D10: 0 | E10: 0 | F10: 0 | G10: 0 | H10: 0 | I10: 0 | J10: 1 | K10: 0 | L10: 0 | M10: 1 | N10: 0 | O10: 0 | P10: 0 | Q10: 1731.677 | R10: =$X$2*A10+$X$3*B10+($X$4)*C10+$X$5*D10+($X$6)*E10+($X$7)*F10+($X$8)*G10+$X$9*H10+($X$10)*I10+($X$11)*J10+$X$12*K10+$X$13*L10+$X$14*M10+($X$15)*N10+($X$16)*O10+($X$17)*P10+($X$18) -> 237.74644 | S10: =Q10-R10 -> 1493.9306 | T10: =(R10-Q10)/Q10 -> -0.8627074 | W10: southeast | X10: -546.82117
A11: 21 | B11: 21.89 | C11: 1 | D11: 0 | E11: 0 | F11: 0 | G11: 0 | H11: 0 | I11: 1 | J11: 0 | K11: 0 | L11: 0 | M11: 1 | N11: 0 | O11: 0 | P11: 0 | Q11: 3180.5101 | R11: =$X$2*A11+$X$3*B11+($X$4)*C11+$X$5*D11+($X$6)*E11+($X$7)*F11+($X$8)*G11+$X$9*H11+($X$10)*I11+($X$11)*J11+$X$12*K11+$X$13*L11+$X$14*M11+($X$15)*N11+($X$16)*O11+($X$17)*P11+($X$18) -> 1063.7573 | S11: =Q11-R11 -> 2116.7528 | T11: =(R11-Q11)/Q11 -> -0.66553878 | W11: southwest | X11: -549.43006
A12: 21 | B12: 22.135 | C12: 1 | D12: 0 | E12: 0 | F12: 0 | G12: 0 | H12: 0 | I12: 0 | J12: 0 | K12: 0 | L12: 1 | M12: 1 | N12: 0 | O12: 0 | P12: 0 | Q12: 2585.8506 | R12: =$X$2*A12+$X$3*B12+($X$4)*C12+$X$5*D12+($X$6)*E12+($X$7)*F12+($X$8)*G12+$X$9*H12+($X$10)*I12+($X$11)*J12+$X$12*K12+$X$13*L12+$X$14*M12+($X$15)*N12+($X$16)*O12+($X$17)*P12+($X$18) -> 2022.178 | S12: =Q12-R12 -> 563.67267 | T12: =(R12-Q12)/Q12 -> -0.21798346 | W12: northwest | X12: 0
A13: 22 | B13: 24.3 | C13: 1 | D13: 0 | E13: 0 | F13: 0 | G13: 0 | H13: 0 | I13: 0 | J13: 1 | K13: 0 | L13: 0 | M13: 1 | N13: 0 | O13: 0 | P13: 0 | Q13: 2150.469 | R13: =$X$2*A13+$X$3*B13+($X$4)*C13+$X$5*D13+($X$6)*E13+($X$7)*F13+($X$8)*G13+$X$9*H13+($X$10)*I13+($X$11)*J13+$X$12*K13+$X$13*L13+$X$14*M13+($X$15)*N13+($X$16)*O13+($X$17)*P13+($X$18) -> 1739.2412 | S13: =Q13-R13 -> 411.22781 | T13: =(R13-Q13)/Q13 -> -0.19122703 | W13: northeast | X13: 374.62163
... A18: 23 | B18: 24.225 | C18: 1 | D18: 0 | E18: 0 | F18: 0 | G18: 0 | H18: 0 | I18: 0 | J18: 0 | K18: 0 | L18: 1 | M18: 1 | N18: 0 | O18: 0 | P18: 0 | Q18: 22395.744 | R18: =$X$2*A18+$X$3*B18+($X$4)*C18+$X$5*D18+($X$6)*E18+($X$7)*F18+($X$8)*G18+$X$9*H18+($X$10)*I18+($X$11)*J18+$X$12*K18+$X$13*L18+$X$14*M18+($X$15)*N18+($X$16)*O18+($X$17)*P18+($X$18) -> 2966.3241 | S18: =Q18-R18 -> 19429.42 | T18: =(R18-Q18)/Q18 -> -0.86754965 | W18: Y-Intercept | X18: -5419.1366
A19: 24 | B19: 23.21 | C19: 1 | D19: 0 | E19: 0 | F19: 0 | G19: 0 | H19: 0 | I19: 1 | J19: 0 | K19: 0 | L19: 0 | M19: 1 | N19: 0 | O19: 0 | P19: 0 | Q19: 25081.768 | R19: =$X$2*A19+$X$3*B19+($X$4)*C19+$X$5*D19+($X$6)*E19+($X$7)*F19+($X$8)*G19+$X$9*H19+($X$10)*I19+($X$11)*J19+$X$12*K19+$X$13*L19+$X$14*M19+($X$15)*N19+($X$16)*O19+($X$17)*P19+($X$18) -> 2206.0381 | S19: =Q19-R19 -> 22875.73 | T19: =(R19-Q19)/Q19 -> -0.91204615
A20: 24 | B20: 22.6 | C20: 1 | D20: 0 | E20: 0 | F20: 0 | G20: 0 | H20: 0 | I20: 0 | J20: 1 | K20: 0 | L20: 0 | M20: 1 | N20: 0 | O20: 0 | P20: 0 | Q20: 2457.502 | R20: =$X$2*A20+$X$3*B20+($X$4)*C20+$X$5*D20+($X$6)*E20+($X$7)*F20+($X$8)*G20+$X$9*H20+($X$10)*I20+($X$11)*J20+$X$12*K20+$X$13*L20+$X$14*M20+($X$15)*N20+($X$16)*O20+($X$17)*P20+($X$18) -> 2111.3618 | S20: =Q20-R20 -> 346.1402 | T20: =(R20-Q20)/Q20 -> -0.14085042
A21: 24 | B21: 24.225 | C21: 1 | D21: 0 | E21: 0 | F21: 0 | G21: 0 | H21: 0 | I21: 0 | J21: 0 | K21: 1 | L21: 0 | M21: 1 | N21: 0 | O21: 0 | P21: 0 | Q21: 2842.7607 | R21: =$X$2*A21+$X$3*B21+($X$4)*C21+$X$5*D21+($X$6)*E21+($X$7)*F21+($X$8)*G21+$X$9*H21+($X$10)*I21+($X$11)*J21+$X$12*K21+$X$13*L21+$X$14*M21+($X$15)*N21+($X$16)*O21+($X$17)*P21+($X$18) -> 2906.0535 | S21: =Q21-R21 -> -63.292704 | T21: =(R21-Q21)/Q21 -> 0.02226452
A22: 25 | B22: 23.465 | C22: 1 | D22: 0 | E22: 0 | F22: 0 | G22: 0 | H22: 0 | I22: 0 | J22: 0 | K22: 0 | L22: 1 | M22: 1 | N22: 0 | O22: 0 | P22: 0 | Q22: 3206.4913 | R22: =$X$2*A22+$X$3*B22+($X$4)*C22+$X$5*D22+($X$6)*E22+($X$7)*F22+($X$8)*G22+$X$9*H22+($X$10)*I22+($X$11)*J22+$X$12*K22+$X$13*L22+$X$14*M22+($X$15)*N22+($X$16)*O22+($X$17)*P22+($X$18) -> 3480.3191 | S22: =Q22-R22 -> -273.82776 | T22: =(R22-Q22)/Q22 -> 0.08539794
A23: 25 | B23: 24.3 | C23: 1 | D23: 0 | E23: 0 | F23: 0 | G23: 0 | H23: 0 | I23: 0 | J23: 1 | K23: 0 | L23: 0 | M23: 1 | N23: 0 | O23: 0 | P23: 0 | Q23: 4391.652 | R23: =$X$2*A23+$X$3*B23+($X$4)*C23+$X$5*D23+($X$6)*E23+($X$7)*F23+($X$8)*G23+$X$9*H23+($X$10)*I23+($X$11)*J23+$X$12*K23+$X$13*L23+$X$14*M23+($X$15)*N23+($X$16)*O23+($X$17)*P23+($X$18) -> 2682.2942 | S23: =Q23-R23 -> 1709.3578 | T23: =(R23-Q23)/Q23 -> -0.38922889
A24: 25 | B24: 22.515 | C24: 1 | D24: 0 | E24: 0 | F24: 0 | G24: 0 | H24: 0 | I24: 0 | J24: 0 | K24: 1 | L24: 0 | M24: 1 | N24: 0 | O24: 0 | P24: 0 | Q24: 3594.1708 | R24: =$X$2*A24+$X$3*B24+($X$4)*C24+$X$5*D24+($X$6)*E24+($X$7)*F24+($X$8)*G24+$X$9*H24+($X$10)*I24+($X$11)*J24+$X$12*K24+$X$13*L24+$X$14*M24+($X$15)*N24+($X$16)*O24+($X$17)*P24+($X$18) -> 2962.3138 | S24: =Q24-R24 -> 631.85708 | T24: =(R24-Q24)/Q24 -> -0.17580051
A25: 25 | B25: 20.8 | C25: 1 | D25: 0 | E25: 0 | F25: 0 | G25: 0 | H25: 0 | I25: 0 | J25: 1 | K25: 0 | L25: 0 | M25: 1 | N25: 0 | O25: 0 | P25: 0 | Q25: 3208.787 | R25: =$X$2*A25+$X$3*B25+($X$4)*C25+$X$5*D25+($X$6)*E25+($X$7)*F25+($X$8)*G25+$X$9*H25+($X$10)*I25+($X$11)*J25+$X$12*K25+$X$13*L25+$X$14*M25+($X$15)*N25+($X$16)*O25+($X$17)*P25+($X$18) -> 2154.0384 | S25: =Q25-R25 -> 1054.7486 | T25: =(R25-Q25)/Q25 -> -0.32870633
A26: 26 | B26: 22.61 | C26: 1 | D26: 0 | E26: 0 | F26: 0 | G26: 0 | H26: 0 | I26: 0 | J26: 0 | K26: 1 | L26: 0 | M26: 0 | N26: 1 | O26: 0 | P26: 0 | Q26: 3176.8159 | R26: =$X$2*A26+$X$3*B26+($X$4)*C26+$X$5*D26+($X$6)*E26+($X$7)*F26+($X$8)*G26+$X$9*H26+($X$10)*I26+($X$11)*J26+$X$12*K26+$X$13*L26+$X$14*M26+($X$15)*N26+($X$16)*O26+($X$17)*P26+($X$18) -> 1727.3136 | S26: =Q26-R26 -> 1449.5023 | T26: =(R26-Q26)/Q26 -> -0.4562752
A27: 26 | B27: 19.8 | C27: 1 | D27: 0 | E27: 0 | F27: 0 | G27: 0 | H27: 0 | I27: 0 | J27: 1 | K27: 0 | L27: 0 | M27: 0 | N27: 1 | O27: 0 | P27: 0 | Q27: 3378.91 | R27: =$X$2*A27+$X$3*B27+($X$4)*C27+$X$5*D27+($X$6)*E27+($X$7)*F27+($X$8)*G27+$X$9*H27+($X$10)*I27+($X$11)*J27+$X$12*K27+$X$13*L27+$X$14*M27+($X$15)*N27+($X$16)*O27+($X$17)*P27+($X$18) -> 753.76962 | S27: =Q27-R27 -> 2625.1404 | T27: =(R27-Q27)/Q27 -> -0.7769193
A28: 26 | B28: 22.23 | C28: 1 | D28: 0 | E28: 0 | F28: 0 | G28: 0 | H28: 0 | I28: 0 | J28: 0 | K28: 1 | L28: 0 | M28: 0 | N28: 1 | O28: 0 | P28: 0 | Q28: 3176.2877 | R28: =$X$2*A28+$X$3*B28+($X$4)*C28+$X$5*D28+($X$6)*E28+($X$7)*F28+($X$8)*G28+$X$9*H28+($X$10)*I28+($X$11)*J28+$X$12*K28+$X$13*L28+$X$14*M28+($X$15)*N28+($X$16)*O28+($X$17)*P28+($X$18) -> 1669.9601 | S28: =Q28-R28 -> 1506.3276 | T28: =(R28-Q28)/Q28 -> -0.47424155
A29: 27 | B29: 23.21 | C29: 1 | D29: 0 | E29: 0 | F29: 0 | G29: 0 | H29: 0 | I29: 1 | J29: 0 | K29: 0 | L29: 0 | M29: 0 | N29: 1 | O29: 0 | P29: 0 | Q29: 3561.8889 | R29: =$X$2*A29+$X$3*B29+($X$4)*C29+$X$5*D29+($X$6)*E29+($X$7)*F29+($X$8)*G29+$X$9*H29+($X$10)*I29+($X$11)*J29+$X$12*K29+$X$13*L29+$X$14*M29+($X$15)*N29+($X$16)*O29+($X$17)*P29+($X$18) -> 1585.4015 | S29: =Q29-R29 -> 1976.4874 | T29: =(R29-Q29)/Q29 -> -0.55489866
A30: 27 | B30: 24.1 | C30: 1 | D30: 0 | E30: 0 | F30: 0 | G30: 0 | H30: 0 | I30: 0 | J30: 1 | K30: 0 | L30: 0 | M30: 0 | N30: 1 | O30: 0 | P30: 0 | Q30: 2974.126 | R30: =$X$2*A30+$X$3*B30+($X$4)*C30+$X$5*D30+($X$6)*E30+($X$7)*F30+($X$8)*G30+$X$9*H30+($X$10)*I30+($X$11)*J30+$X$12*K30+$X$13*L30+$X$14*M30+($X$15)*N30+($X$16)*O30+($X$17)*P30+($X$18) -> 1717.1205 | S30: =Q30-R30 -> 1257.0055 | T30: =(R30-Q30)/Q30 -> -0.42264701
... A1339: 18 | B1339: 17.29 | C1339: 0 | D1339: 0 | E1339: 0 | F1339: 1 | G1339: 1 | H1339: 1 | I1339: 0 | J1339: 0 | K1339: 0 | L1339: 1 | M1339: 1 | N1339: 0 | O1339: 0 | P1339: 0 | Q1339: 12829.455 | R1339: =$X$2*A1339+$X$3*B1339+($X$4)*C1339+$X$5*D1339+($X$6)*E1339+($X$7)*F1339+($X$8)*G1339+$X$9*H1339+($X$10)*I1339+($X$11)*J1339+$X$12*K1339+$X$13*L1339+$X$14*M1339+($X$15)*N1339+($X$16)*O1339+($X$17)*P1339+($X$18) -> 23696.708 | S1339: =Q1339-R1339 -> -10867.253 | T1339: =(R1339-Q1339)/Q1339 -> 0.84705489

Sheet Answer_Check_Regression_Table
A1: SUMMARY OUTPUT
A3: Regression Statistics
A4: Multiple R | B4: 0.86882817
A5: R Square | B5: 0.75486239
A6: Adjusted R Square | B6: 0.75018959
A7: Standard Error | B7: 6025.1967
A8: Observations | B8: 1338
A10: ANOVA
B11: df | C11: SS | D11: MS | E11: F | F11: Significance F
A12: Regression | B12: 16 | C12: 1.4800906e+11 | D12: 9.250566e+09 | E12: 313.61908 | F12: 0
A13: Residual | B13: 1324 | C13: 4.8065166e+10 | D13: 36302995
A14: Total | B14: 1340 | C14: 1.9607422e+11
B16: Coefficients | C16: Standard Error | D16: t Stat | E16: P-value | F16: Lower 95% | G16: Upper 95%
A17: Intercept | B17: -5419.1366 | C17: 1997.8219 | D17: -2.7125223 | E17: 0.0067638255 | F17: -9338.3785 | G17: -1499.8947
A18: age | B18: 314.35099 | C18: 32.910137 | D18: 9.5517983 | E18: 5.9234823e-21 | F18: 249.78928 | G18: 378.91269
A19: bmi | B19: 150.93022 | C19: 53.724421 | D19: 2.8093409 | E19: 0.0050373057 | F19: 45.535938 | G19: 256.32449
A20: BMI_Healthy | B20: -2875.5181 | C20: 810.83119 | D20: -3.5463832 | E20: 0.00040418376 | F20: -4466.1721 | G20: -1284.864
A21: BMI_Overweight | B21: 0 | C21: 0 | D21: 65535 | E21: #NUM! | F21: 0 | G21: 0
A22: BMI_Slightly_Overweight | B22: -2592.2956 | C22: 555.59177 | D22: -4.6658279 | E22: #NUM! | F22: -3682.2318 | G22: -1502.3594
A23: BMI_Underweight | B23: -3294.8153 | C23: 1652.8407 | D23: -1.9934258 | E23: 0.046419739 | F23: -6537.2876 | G23: -52.342927
A24: Gender | B24: -113.82489 | C24: 330.91809 | D24: -0.34396695 | E24: 0.73092576 | F24: -763.00588 | G24: 535.35611
A25: Smoker | B25: 23881.962 | C25: 411.59304 | D25: 58.023241 | E25: 0 | F25: 23074.516 | G25: 24689.407
A26: southeast | B26: -546.82117 | C26: 478.67284 | D26: -1.1423693 | E26: 0.25350707 | F26: -1485.8611 | G26: 392.21878
A27: southwest | B27: -549.43006 | C27: 474.50852 | D27: -1.1578929 | E27: 0.24711656 | F27: -1480.3006 | G27: 381.44051
A28: northwest | B28: 0 | C28: 0 | D28: 65535 | E28: #NUM! | F28: 0 | G28: 0
A29: northeast | B29: 374.62163 | C29: 473.96149 | D29: 0.79040521 | E29: #NUM! | F29: -555.1758 | G29: 1304.4191
A30: Young Adult | B30: 0 | C30: 0 | D30: 65535 | E30: #NUM! | F30: 0 | G30: 0
A31: Adult | B31: -1563.6895 | C31: 596.53695 | D31: -2.6212786 | E31: #NUM! | F31: -2733.9503 | G31: -393.4288
A32: Mature Age Adult | B32: -2358.8165 | C32: 975.87568 | D32: -2.4171281 | E32: 0.015777935 | F32: -4273.2478 | G32: -444.38523
A33: Senior | B33: -2149.696 | C33: 1508.6485 | D33: -1.4249152 | E33: 0.1544174 | F33: -5109.2982 | G33: 809.90613

Sheet Intermediate Desc. Statistics
A1: Descriptive Statistics Analysis - Part II
A2: We've introduced you now to the concepts of intermediate statistics.
A3: Often in our data analysis, we need to move beyond simple statistics covering mean, mode, median and histograms and dive a bit deeper in our analysis.
A5: Using our previous Walmart example, say we've identified the average sales on the weekends versus weekdays and we've created a histogram showing the overall distribution of sales.
A6: What if we want to understand just how distributed the data is via the quartiles, or to view how much variability in sales exist for a specific day?
A7: Lastly, what about if we want to examine the relationship between sales and the discounts provided?
A9: Well, to answer those questions we'd seek to use quartiles, box plots and correlation analyses to better understand how we could answer these questions!
A10: With that in mind, let's get started!
A12: Previously we observed the overall distribution of medical insurance charges via a Histogram.
A13: While this helped us understand how medical charges were distributed - we don't have a hard metric regarding just how dispersed the medical insurance charges are.
A14: Wouldn't it be nice if we had a method to split our medical insurance into 4 neat quartiles, to help us better understand just how distributed our data is?
A15: That's exactly what we'll do in this question!
... A18: Note: We use the phrase quartile and percentile interchangeably. Use the Quartile() function to answer this question.
B19: Percentile | C19: 25 | D19: 50 | E19: 75 | F19: 100
C20: =QUARTILE('FamInsureCo Int. Stats Data'!$Q:$Q,1) -> 4740.2872 | D20: =QUARTILE('FamInsureCo Int. Stats Data'!$Q:$Q,2) -> 9382.033 | E20: =QUARTILE('FamInsureCo Int. Stats Data'!$Q:$Q,3) -> 16639.913 | F20: =QUARTILE('FamInsureCo Int. Stats Data'!$Q:$Q,4) -> 63770.428
B22: Interquantile Range | C22: =E20-C20 -> 11899.625
A25: Having now calculated the Interquartile Range, we have a better idea regarding how distributed the values are in our Medical Insurance Charges dataset.
A26: You might have recalled that we previously covered Box and Whisker Plots that enable us to see how the data is distributed based off quartiles.
A27: We've identified that smoking status, age and gender all seem to impact medical insurance charges to an extent.
A28: We haven't yet explored regions - so we'll look at this next with a box plot.
A29: Q8. Create a box plot using the Medical Insurance Charges and the Regions column, showing how costs are distributed across different living regions.
A30: Note: We've included an example of what your box and whisker plot should look like below!
A50: Observing our Box Plots, we don't see any particular changes with respect to Median Medical Charges.
A51: How about if we filter on Smoking Status? Do we see any substantial changes here?
A52: Q9. Create 2 Box Plots where Smoking Status = Yes and Smoking Status = No, using the Region and Medical Insurance Charges Columns. Does there appear to be a difference in costs regarding geography?
A53: Note: We've included an example for you so you'll know what to expect when you create your visualisation!
B54: Place your chart below here (Smoking = No ) | F54: Place your chart below here (Smoking = Yes )
A70: *Costslook to stay the same between regions. | C70: No smoking mean: | D70: =AVERAGEIF('FamInsureCo Desc. Stats Data'!$D:$D,"No",'FamInsureCo Desc. Stats Data'!$F:$F) -> 8434.2683 | E70: =(D71-D70)/D71 -> 0.73684221
C71: Yes smoking mean: | D71: =AVERAGEIF('FamInsureCo Desc. Stats Data'!$D:$D,"Yes",'FamInsureCo Desc. Stats Data'!$F:$F) -> 32050.232
A72: It seems that the prevalence of smoking seems to be quite a substantial factor when taking into lifestyle factors.
A73: Whilst we might be tempted to discount looking at gender, we haven't looked at the medical insurance charges of males/females who smoke. Let's investigate!
A74: Q10. Create two box plots using the Medical Insurance Column and the Sex Column. Please filter your Box Plots to account for the periods where the Smoking Status = Yes or the Smoking Status = No. From your box plots, what do you observe?
A75: Note: We've included an example for you so you'll know what to expect when you create your visualisation!
B76: Place your chart below here (Smoking = No ) | F76: Place your chart below here (Smoking = Yes )
A96: Smoking still has a substantial impact on insurance charges while gender does not impact medical insurance charges as much.
A98: Great job so far! We're now ready to move onto the last part of our assignment - correlations!
A99: We know that correlation helps us understand the relationship between two variables and whether they share a linear relationship or not.
A100: Here we've noted age, BMI classification and regions - all might be related to our medical insurance charges.
A101: Q11. Using the CORREL() function, calculate the Correlation Value using the BMI and Medical Insurance Columns.
A102: Note: If you're stuck, please reference this link: https://support.microsoft.com/en-us/office/correl-function-995dcef7-0c0a-4bed-a3fb-239d7b68ca92
A103: What do you observe from the Correlation Value?
A104: Fill in the Correlation ( R ) value below
C105: BMI
B106: Medical Insurance Charges | C106: =CORREL('FamInsureCo Desc. Stats Data'!$C:$C,'FamInsureCo Desc. Stats Data'!$F:$F) -> 0.19834097
A107: R squared = 0.40 or 40%
A109: Now you might be surprised. Previously we thought we saw some clear relationships between BMI and Medical Insurance Charges.
A110: Again, our R Value is a reflection of the linear relationship between medical charges and BMI. We have lots of noise in our data.
A111: We've already prepared the data for you in the FamInsureCo Int Stats Data Tab, so there's no conversions you need to do.
A112: Q12. Using the CORREL() function, fill out the Corrrelation Table below.
A113: Fill in the Correlation ( R ) value below
C115: BMI | D115: BMI_Healthy | E115: BMI_Overweight | F115: BMI_Slightly_Overweight | G115: BMI_Underweight
B116: Medical Insurance Charges | C116: =CORREL('FamInsureCo Int. Stats Data'!$B:$B,'FamInsureCo Int. Stats Data'!$Q:$Q) -> 0.19834097 | D116: =CORREL('FamInsureCo Int. Stats Data'!$C:$C,'FamInsureCo Int. Stats Data'!$Q:$Q) -> -0.10651203 | E116: =CORREL('FamInsureCo Int. Stats Data'!$D:$D,'FamInsureCo Int. Stats Data'!$Q:$Q) -> 0.19685713 | F116: =CORREL('FamInsureCo Int. Stats Data'!$E:$E,'FamInsureCo Int. Stats Data'!$Q:$Q) -> -0.11776843 | G116: =CORREL('FamInsureCo Int. Stats Data'!$F:$F,'FamInsureCo Int. Stats Data'!$Q:$Q) -> -0.044959617
A119: Now you've probably observed that since we've converted some of our textual categories, to numerical columns, we can now calculate some additional correlations.
A120: This is what we've done for our remaining textual columns where we've done all the categorical conversions for you!
A121: Q13. Using the CORREL() function, fill out the Correlation Table below.
A122: Fill in the Correlation ( R ) value below
C124: age | D124: bmi | E124: BMI_Healthy | F124: BMI_Overweight | G124: BMI_Slightly_Overweight | H124: BMI_Underweight | I124: Biological Marker | J124: Smoker | K124: southeast | L124: southwest | M124: northwest | N124: northeast | O124: Young Adult | P124: Adult | Q124: Mature Age Adult | R124: Senior
B125: Medical Insurance Charges | C125: =CORREL('FamInsureCo Int. Stats Data'!A:A,'FamInsureCo Int. Stats Data'!$Q:$Q) -> 0.29900819 | D125: =CORREL('FamInsureCo Int. Stats Data'!B:B,'FamInsureCo Int. Stats Data'!$Q:$Q) -> 0.19834097 | E125: =CORREL('FamInsureCo Int. Stats Data'!C:C,'FamInsureCo Int. Stats Data'!$Q:$Q) -> -0.10651203 | F125: =CORREL('FamInsureCo Int. Stats Data'!D:D,'FamInsureCo Int. Stats Data'!$Q:$Q) -> 0.19685713 | G125: =CORREL('FamInsureCo Int. Stats Data'!E:E,'FamInsureCo Int. Stats Data'!$Q:$Q) -> -0.11776843 | H125: =CORREL('FamInsureCo Int. Stats Data'!F:F,'FamInsureCo Int. Stats Data'!$Q:$Q) -> -0.044959617 | I125: =CORREL('FamInsureCo Int. Stats Data'!G:G,'FamInsureCo Int. Stats Data'!$Q:$Q) -> 0.057292062 | J125: =CORREL('FamInsureCo Int. Stats Data'!H:H,'FamInsureCo Int. Stats Data'!$Q:$Q) -> 0.78725143 | K125: =CORREL('FamInsureCo Int. Stats Data'!I:I,'FamInsureCo Int. Stats Data'!$Q:$Q) -> 0.073981552 | L125: =CORREL('FamInsureCo Int. Stats Data'!J:J,'FamInsureCo Int. Stats Data'!$Q:$Q) -> -0.043210029 | M125: =CORREL('FamInsureCo Int. Stats Data'!K:K,'FamInsureCo Int. Stats Data'!$Q:$Q) -> -0.039904864 | N125: =CORREL('FamInsureCo Int. Stats Data'!L:L,'FamInsureCo Int. Stats Data'!$Q:$Q) -> 0.0063487713 | O125: =CORREL('FamInsureCo Int. Stats Data'!M:M,'FamInsureCo Int. Stats Data'!$Q:$Q) -> -0.18817795 | P125: =CORREL('FamInsureCo Int. Stats Data'!N:N,'FamInsureCo Int. Stats Data'!$Q:$Q) -> -0.11473525 | Q125: =CORREL('FamInsureCo Int. Stats Data'!O:O,'FamInsureCo Int. Stats Data'!$Q:$Q) -> 0.1376657 | R125: =CORREL('FamInsureCo Int. Stats Data'!P:P,'FamInsureCo Int. Stats Data'!$Q:$Q) -> 0.20111838
A128: Now that we've got our correlation values calculated against our Medical Insurance Variable. Let's visualise this in an organised manner with a Bar Chart sorting the correlation values in descending order!
A129: Q14. Using the Correlation Table you created in Q14, create a Correlated Bar Plot, with the Correlation Values organised in descending order.
B132: Smoker | C132: =J125 -> 0.78725143
B133: age | C133: =C125 -> 0.29900819
B134: Senior | C134: =R125 -> 0.20111838
B135: bmi | C135: =D125 -> 0.19834097
B136: BMI_Overweight | C136: =F125 -> 0.19685713
B137: Mature Age Adult | C137: =Q125 -> 0.1376657
B138: southeast | C138: =K125 -> 0.073981552
B139: Gender | C139: =I125 -> 0.057292062
B140: northeast | C140: =N125 -> 0.0063487713
B141: northwest | C141: =M125 -> -0.039904864
B142: southwest | C142: =L125 -> -0.043210029
B143: BMI_Underweight | C143: =H125 -> -0.044959617
B144: BMI_Healthy | C144: =E125 -> -0.10651203
B145: Adult | C145: =P125 -> -0.11473525
B146: BMI_Slightly_Overweight | C146: =G125 -> -0.11776843
B147: Young Adult | C147: =O125 -> -0.18817795
A149: Now whilst correlation is helpful, this doesn't tell us the whole story.
A150: Rather, we want to be able to create a regressive model that helps us understand whether or not we have a regressive equation that helps us to predict the medical insurance charges.
A151: Now to create a linear regression model, we're going to have to retrieve the slopes (coefficients) for each variable.
A152: To streamline your experience, we've calculated these co-efficients for you that you'll utilize in the next question!
A153: Otherwise in Excel Desktop you can use either the Data Analysis Toolpak or the LINEST() function we taught you earlier to retrieve these coefficients.
A154: Now it's time for us to interpret these coefficients!
A156: Q15. Using the outputs provided above, what do they tell you regarding which variables appear to have a positive relationship with Medical Insurance Charges?
A157: What does the R Squared tell you about the Linear Regression Fit?
A158: We've included a copy of what the output might look like below so you can check your coefficients!
B160: age | C160: bmi | D160: BMI_Healthy | E160: BMI_Overweight | F160: BMI_Slightly_Overweight | G160: BMI_Underweight | H160: Biological Marker | I160: Smoker | J160: southeast | K160: southwest | L160: northwest | M160: northeast | N160: Young Adult | O160: Adult | P160: Mature Age Adult | Q160: Senior
A161: Coefficient Value | B161: 314.35099 | C161: 150.93022 | D161: -2875.5181 | E161: 0 | F161: -2592.2956 | G161: -3294.8153 | H161: -113.82489 | I161: 23881.962 | J161: -546.82117 | K161: -549.43006 | L161: 0 | M161: 374.62163 | N161: 0 | O161: -1563.6895 | P161: -2358.8165 | Q161: -2149.696
A163: R Squared Value | B163: 0.75486239
A164: Y-Intercept | B164: -5419.1366
A166: Put your answer below
A167: The broader categories including smoking, age, and BMI al have positive correlations with the medical insurance charges. The R squared of 75% shows that there is a relatively strong linear regression fit.
A171: Now that we've got all our coefficients, we can create our own multiple regressive equation to forecast our Medical Insurance Costs!
A172: As you've learnt previously, we've covered the concept of regression where you're seeking to model some dependent variable (e.g. Medical Insurance Charges) using a series of independent predictor variables (e.g. Smoker Status, Age, BMI etc.)
A173: Think of the regressive equation in this manner: Y( Medical Insurance Charges ) = SomeCoefficientValue x Smoker Values + SomeCoefficient x Age Values …... + Y Intercept. This is what we are seeking to model below with the regressive equation highlighted.
A175: Q16. Using the coefficients we've provided in the FamInsureCo Int. Stats Data Tab (Columns W & X), create a regressive equation and fill in the column called Predicted Charges (Column R) in the FamInsureCo Int. Stats Data Tab!
A176: Upon completion of this, create a Line Chart showing how the Actual Medical Insurance Charges compares against your Predicted Charges as per the image we've demonstrated.
A202: Lastly, we need to calculate the error, or the difference, between our Regression Equation and the Actual Medical Insurance Charges.
A203: Q17. In Column S, titled Error subtract the Regression Equation Value from the Actual Medical Insurance Charges for each row. In Column T, titled Error_Pct, subtract the Regression Equation Value from the Actual Medical Insurance Charges for each row before dividing this by the Actual Medical Insurance Charges.
A204: e.g. Our Regression Equation Result is $1,000. The Actual Medical Insurance Charge is $1,300. We would then go: (1000 - 1300)/1300 --> -23%
A205: After this, calculate the median using the 'Error %' Column and place this in the box below.
...
